[{"key":"AKDV.Errors.Error","value":"Error"},{"key":"AKDV.Errors.NaN","value":"unknown "},{"key":"AKDV.Errors.Unknown","value":"unknown "},{"key":"AKDV.Errors.EmptyAtPercentile","value":"The current percentile setting excludes any results in this range."},{"key":"AKDV.Errors.FetchTitle","value":"Fetch Error"},{"key":"AKDV.Errors.Fetch","value":"Sorry, there was no response from the requested server. Please contact support for assistance."},{"key":"AKDV.Errors.MissingParam","value":"The URL is missing a required parameter"},{"key":"AKDV.Errors.DWSBConnection","value":"Sorry, there was a error connecting to the server. Please try again or contact support for assistance."},{"key":"AKDV.Errors.NoNotebook","value":"Sorry, the associated notebook was not found. Please contact support for assistance."},{"key":"AKDV.Errors.Unauthorized","value":"Sorry, there was a permissions error executing the query. Please contact support for assistance."},{"key":"AKDV.Errors.Unauthenticated","value":"Sorry, an authentication error occurred. Please contact support for assistance."},{"key":"AKDV.Errors.Tenant","value":"Sorry, tenant not found. Please reload mPulse."},{"key":"AKDV.Errors.MissingFilters","value":"Sorry, this widget is missing required filters. Please ensure that Date/Time and Domain filters are applied."},{"key":"AKDV.Errors.TimeRangeTooShort","value":"Sorry, the time range defined in the Date/Time filter is too short. Please increase the range."},{"key":"AKDV.Errors.ChartSchema","value":"Sorry, the time requested chart schema was not found."},{"key":"AKDV.Errors.UnsupportedTimer","value":"Sorry, this widget does not support the selected timer."},{"key":"AKDV.Errors.ConversionMetric","value":"Sorry, this widget requires a conversion metric. Please set a valid Metric filter for the dashboard or widget."},{"key":"AKDV.Errors.Parse","value":"Sorry, there was an error parsing the data. Please contact support for assistance."},{"key":"AKDV.Errors.Execution","value":"Sorry, there was an error executing the query. Please contact support for assistance."},{"key":"AKDV.Errors.UnknownError","value":"Sorry, something went wrong. Please try again or contact support for assistance."},{"key":"AKDV.Errors.NoData","value":"Sorry, the request was successful but there was no result. Please try a different time range or contact support for assistance."},{"key":"AKDV.Errors.InvalidData","value":"Sorry, the received data appears to be invalid. Please contact support for assistance."},{"key":"AKDV.Errors.UnsupportedOrigin","value":"Sorry, the specified data url is not from a supported origin. Please try again or contact support for assistance."},{"key":"AKDV.Errors.Datasource.File.XMLHTTP.Get","value":"Data Request Error"},{"key":"AKDV.Errors.Datasource.GraphQL.XMLHTTP.Post","value":"GraphQL Submission Error"},{"key":"AKDV.Errors.Localization.XMLHTTP.Get","value":"Localization Request Failed"},{"key":"AKDV.Errors.Repository.XMLHTTP.Get","value":"Repository Request Failed"},{"key":"AKDV.Status.Initializing","value":"Initializing"},{"key":"AKDV.Status.AwaitingMpulse","value":"Awaiting mPulse filters"},{"key":"AKDV.Status.Connecting","value":"Connecting"},{"key":"AKDV.Status.Connected","value":"Connected"},{"key":"AKDV.Status.Requesting","value":"Requesting data"},{"key":"AKDV.Status.RequestingFilters","value":"Requesting mPulse filters"},{"key":"AKDV.Status.Analyzing","value":"Analyzing data"},{"key":"AKDV.Status.ServerProcessing","value":"Server processing request"},{"key":"AKDV.Status.Rendering","value":"Rendering chart"},{"key":"AKDV.Status.History.Toggle","value":"Toggle Visibility (Shift+i)"},{"key":"AKDV.Columns.DeviceTypeName","value":"Device Type"},{"key":"AKDV.Columns.PageGroupName","value":"Page Group"},{"key":"AKDV.Columns.UserAgentName","value":"Browser Family"},{"key":"AKDV.Columns.CountryCode","value":"Country"},{"key":"AKDV.Columns.MediaType","value":"Media type"},{"key":"AKDV.Columns.Host","value":"Host"},{"key":"AKDV.Columns.Path","value":"Path"},{"key":"AKDV.Metrics.orderValue","value":"Order Value"},{"key":"AKDV.Metrics.sessionDuration","value":"Session Duration"},{"key":"AKDV.Metrics.conversionRate","value":"Conversion Rate"},{"key":"AKDV.Metrics.bounceRate","value":"Bounce Rate"},{"key":"AKDV.Metrics.lingerTime","value":"Time on Page"},{"key":"AKDV.Metrics.sessionLength","value":"Pages per Session"},{"key":"AKDV.Metrics.totalRevenue","value":"Total Revenue"},{"key":"AKDV.Metrics.sessions","value":"Sessions"},{"key":"AKDV.Metrics.beacons","value":"Beacons"},{"key":"AKDV.Descriptions.orderValue","value":"The average value of converted sessions"},{"key":"AKDV.Descriptions.sessionDuration","value":"The average duration of a session, measured from the first navigation to the user leaving the last page"},{"key":"AKDV.Descriptions.conversionRate","value":"The percentage of sessions which resulted in a conversion or revenue metric greater than zero"},{"key":"AKDV.Descriptions.bounceRate","value":"The percentage of sessions which have a session length of one page"},{"key":"AKDV.Descriptions.lingerTime","value":"The average time spent viewing pages, excluding the time taken to load the page"},{"key":"AKDV.Descriptions.sessionLength","value":"The average number of pages loaded in a session"},{"key":"AKDV.Descriptions.totalRevenue","value":"The sum of all revenue metrics reported across the sessions in the given time period"},{"key":"AKDV.Descriptions.sessions","value":"A session is a group of beacons recorded for a single user within an inactivity time threshold (by default 30 minutes)"},{"key":"AKDV.Descriptions.beacons","value":"A beacon is equivalent to a page view, or application navigation depending on your configuration"},{"key":"AKDV.Strings.RootBreadcrumbName","value":"Root"},{"key":"AKDV.Tooltips.Title.Copy","value":"Copy"},{"key":"AKDV.Tooltips.Description.Copy","value":"Copied to Clipboard"}]